[
  {
    "id": "11",
    "title": "Koos Dorssers",
    "content": "We zouden graag iemand vinden die onze hond 3x per week uit kan laten.",
    "date": "2020-10-04 23:33:22",
    "location": "Venlo",
    "address" : "Beethovenstraat 14, 5914 BN Venlo. Telefoon; 06-12347895",
    "phonenumber" : "0627305326",
    "general" : "We kunnen redelijk flexibel in de avonduren inplannen.",
    "dograce" : "Straat maal straat. Lijkt op Tekkel"
  },
  {
    "id": "12",
    "title": "Lutegarda Vasconcelos",
    "content": "We zouden graag iemand vinden die onze hond 3x per week uit kan laten.",
    "date": "2020-01-28 07:50:06",
    "location": "Velden",
    "address" : "Beethovenstraat 14, 5911 AA Velden. Telefoon; 06-12347895",
    "phone" : "0627305326",
    "general" : "Matig. Weinig tijdkeus. Vriendelijk.",
    "dograce" : "Tekkel"
  },
  {
    "id": "13",
    "title": "Koos Dorssers",
    "content": "We zouden graag iemand vinden die onze hond 3x per week uit kan laten.",
    "date": "2021-11-03 13:43:01",
    "location": "Baarlo",
    "address" : "Beethovenstraat 14, 5911 RR Baarlo. Telefoon; 06-12347895",
    "phone" : "0627305326",
    "general" : "Redelijk. Wat zakelijk. Punctueel.",
    "dograce" : "Pincher"
  },
  {
    "id": "14",
    "title": "Koos Dorssers",
    "content": "We zouden graag iemand vinden die onze hond 3x per week uit kan laten.",
    "date": "2021-06-23 00:48:31",
    "location": "Tegelen",
    "address" : "Beethovenstraat 14, 5912 GG Tegelen. Telefoon; 06-12347895",
    "phone" : "0627305326",
    "general" : "Goed. Flexibel. Kort en zakelijk.",
    "dograce" : "Labrador"
  },
  {
    "id": "15",
    "title": "Koos Dorssers",
    "content": "We zouden graag iemand vinden die onze hond 3x per week uit kan laten.",
    "date": "2020-03-25 16:18:31",
    "location": "Blerick",
    "address" : "Beethovenstraat 14, 5913 AA Blerick. Telefoon; 06-12347895",
    "phone" : "0627305326",
    "general" : "Goed. Erg punctueel. Vriendelijk.",
    "dograce" : "Chihuaha
  },
  {
    "id": "16",
    "title": "Koos Dorssers",
    "content": "We zouden graag iemand vinden die onze hond 3x per week uit kan laten.",
    "date": "2020-03-13 12:47:13",
    "location": "Maasbree",
    "address" : "Beethovenstraat 14, 5914 DD  Maasbree. Telefoon; 06-12347895",
    "phone" : "0627305326",
    "general" : "Matig. Soms laat. Leuke mensen.",
    "dograce" : "Duitse Herder"
  }
]